wagtailhavetheabilitytoactuallyseefieldsintheadmin-1.0.0.dist-info/METADATA
wagtailhavetheabilitytoactuallyseefieldsintheadmin-1.0.0.dist-info/top_level.txt
wagtailhavetheabilitytoactuallyseefieldsintheadmin-1.0.0.dist-info/DESCRIPTION.rst
wagtailhavetheabilitytoactuallyseefieldsintheadmin-1.0.0.dist-info/RECORD
wagtailhavetheabilitytoactuallyseefieldsintheadmin-1.0.0.dist-info/WHEEL
wagtailhavetheabilitytoactuallyseefieldsintheadmin-1.0.0.dist-info/metadata.json
wagtailhavetheabilitytoactuallyseefieldsintheadmin/wagtail_hooks.py
wagtailhavetheabilitytoactuallyseefieldsintheadmin/__init__.py
wagtailhavetheabilitytoactuallyseefieldsintheadmin/static/wagtailhavetheabilitytoactuallyseefieldsintheadmin/css/wagtailhavetheabilitytoactuallyseefieldsintheadmin.css
