Metadata-Version: 2.0
Name: wagtailhavetheabilitytoactuallyseefieldsintheadmin
Version: 1.0.0
Summary: A quick fix for when the StreamField goes too deep.
Home-page: https://github.com/alexgleason/wagtailhavetheabilitytoactuallyseefieldsintheadmin
Author: Alex Gleason
Author-email: alex@alexgleason.me
License: MIT
Keywords: development
Platform: UNKNOWN
Classifier: Environment :: Web Environment
Classifier: Framework :: Django
Classifier: Intended Audience :: Developers
Classifier: Operating System :: OS Independent
Classifier: Programming Language :: Python
Classifier: Topic :: Internet :: WWW/HTTP
Classifier: Topic :: Internet :: WWW/HTTP :: Dynamic Content
Requires-Dist: wagtail (>=0.8.7)
Requires-Dist: Django (>=1.7.1)
